penknife/__init__.py
penknife/main.py
penknife/msg.py
penknife/pdf.py
penknife/rpa.py
penknife/sys.py
penknife/vba.py
penknife/web.py
penknife-2021.5.15.dist-info/LICENSE.txt
penknife-2021.5.15.dist-info/METADATA
penknife-2021.5.15.dist-info/WHEEL
penknife-2021.5.15.dist-info/top_level.txt
penknife-2021.5.15.dist-info/RECORD
